bifs/.DS_Store
bifs/__init__.py
bifs/_version.py
bifs/bifs_gui.py
bifs/bifscore.py
bifs/bifsexception.py
bifs/pset_dialogs.py
bifs/bases/__init__.py
bifs/bases/fourier.py
bifs/bifs_util/EmpiricalScanner.py
bifs/bifs_util/__init__.py
bifs/bifs_util/util.py
bifs/priors/AbstractPrior.py
bifs/priors/EmpiricalPrior.py
bifs/priors/FunctionalPrior.py
bifs/priors/__init__.py
bifs-0.9.5.dist-info/LICENSE
bifs-0.9.5.dist-info/METADATA
bifs-0.9.5.dist-info/WHEEL
bifs-0.9.5.dist-info/entry_points.txt
bifs-0.9.5.dist-info/top_level.txt
bifs-0.9.5.dist-info/RECORD
