Metadata-Version: 2.1
Name: bifs
Version: 0.9.5
Summary: Bayesian Imaging in Fourier Space (BIFS)
Home-page: https://github.com/ucsf-deb/bifs
Author: John Kornak, Karl Young, Ross Boylan
Author-email: john.kornak@ucsf.edu,kyoung21b2000@gmail.com
Maintainer-email: ross.boylan@ucsf.edu,bifs@ucsf.edu
License: Copyright (c) 2021, University of California and The National Institues of Health. All rights reserved.        
Platform: UNKNOWN
Classifier: Programming Language :: Python :: 3
Classifier: Development Status :: 4 - Beta
Classifier: Intended Audience :: Science/Research
Classifier: Natural Language :: English
Classifier: Operating System :: OS Independent
Classifier: Topic :: Multimedia :: Graphics
Classifier: Topic :: Scientific/Engineering :: Image Processing
Classifier: Topic :: Scientific/Engineering :: Visualization
License-File: LICENSE
Requires-Dist: imageio
Requires-Dist: jsonpickle
Requires-Dist: matplotlib
Requires-Dist: nibabel
Requires-Dist: numpy (>=1.17)
Requires-Dist: PyQt5
Requires-Dist: scipy
Provides-Extra: ni
Requires-Dist: nibabel ; extra == 'ni'
Provides-Extra: tests
Requires-Dist: pytest ; extra == 'tests'
